ratvec/__init__.py
ratvec/__main__.py
ratvec/classifiers.py
ratvec/cli.py
ratvec/constants.py
ratvec/eval_utils.py
ratvec/evaluation.py
ratvec/kernel_utils.py
ratvec/metrics.py
ratvec/protein_seq_reader.py
ratvec/similarity.py
ratvec/similarity_fast.pyx
ratvec/similarity_slow.py
ratvec/train.py
ratvec/utils.py
ratvec/version.py
ratvec-0.1.2.dist-info/LICENSE
ratvec-0.1.2.dist-info/METADATA
ratvec-0.1.2.dist-info/WHEEL
ratvec-0.1.2.dist-info/entry_points.txt
ratvec-0.1.2.dist-info/top_level.txt
ratvec-0.1.2.dist-info/RECORD
