Metadata-Version: 2.1
Name: ratvec
Version: 0.1.2
Summary: Generating dense embeddings for proteins using kernel PCA
Home-page: https://github.com/ratvec/ratvec
Author: Eduardo Brito
Author-email: eduardo.alfredo.brito.chacon@iais.fraunhofer.de
Maintainer: Eduardo Brito
Maintainer-email: eduardo.alfredo.brito.chacon@iais.fraunhofer.de
License: Apache 2.0 License
Download-URL: https://github.com/ratvec/ratvec/releases
Project-URL: Bug Tracker, https://github.com/ratvec/ratvec/issues
Project-URL: Documentation, https://ratvec.readthedocs.io
Keywords: Representation Learning,Kernel PCA,Principle Component Analysis,PCA
Platform: UNKNOWN
Classifier: Development Status :: 4 - Beta
Classifier: Environment :: Console
Classifier: Intended Audience :: Developers
Classifier: Intended Audience :: Science/Research
Classifier: License :: OSI Approved :: Apache Software License
Classifier: Operating System :: OS Independent
Classifier: Programming Language :: Python
Classifier: Programming Language :: Python :: 3.7
Classifier: Programming Language :: Python :: 3.6
Classifier: Programming Language :: Python :: 3 :: Only
Classifier: Topic :: Scientific/Engineering :: Bio-Informatics
Classifier: Topic :: Scientific/Engineering :: Mathematics
Classifier: Topic :: Scientific/Engineering :: Artificial Intelligence
Requires-Python: >=3.6
Requires-Dist: click (>=7.0)
Requires-Dist: requests
Requires-Dist: distance
Requires-Dist: numpy
Requires-Dist: scipy
Requires-Dist: tqdm
Requires-Dist: sklearn
Requires-Dist: cython
Requires-Dist: click
Requires-Dist: biopython
